diagnose/__init__.py
diagnose/breakpoints.py
diagnose/instruments.py
diagnose/managers.py
diagnose/patchlib.py
diagnose/probes.py
diagnose/test_fixtures.py
diagnose-5.0.1.dist-info/LICENSE
diagnose-5.0.1.dist-info/METADATA
diagnose-5.0.1.dist-info/WHEEL
diagnose-5.0.1.dist-info/top_level.txt
diagnose-5.0.1.dist-info/RECORD
