Metadata-Version: 2.1
Name: diagnose
Version: 5.0.1
Summary: A library for instrumenting Python code at runtime.
Home-page: https://github.com/Crunch-io/diagnose
Author: Robert Brewer
Author-email: dev@crunch.io
License: UNKNOWN
Platform: UNKNOWN
Requires-Python: >=3.6
License-File: LICENSE
Requires-Dist: hunter (>=2.2.0)
